dbdaora/__init__.py
dbdaora/cache.py
dbdaora/circuitbreaker.py
dbdaora/entity.py
dbdaora/exceptions.py
dbdaora/hashring.py
dbdaora/keys.py
dbdaora/py.typed
dbdaora/query.py
dbdaora/boolean/__init__.py
dbdaora/boolean/conftest.py
dbdaora/boolean/factory.py
dbdaora/boolean/service.py
dbdaora/boolean/repositories/__init__.py
dbdaora/boolean/repositories/datastore.py
dbdaora/data_sources/__init__.py
dbdaora/data_sources/fallback/__init__.py
dbdaora/data_sources/fallback/datastore.py
dbdaora/data_sources/fallback/dict.py
dbdaora/data_sources/fallback/mongodb.py
dbdaora/data_sources/memory/__init__.py
dbdaora/data_sources/memory/aioredis.py
dbdaora/data_sources/memory/dict.py
dbdaora/geospatial/__init__.py
dbdaora/geospatial/conftest.py
dbdaora/geospatial/entity.py
dbdaora/geospatial/factory.py
dbdaora/geospatial/query.py
dbdaora/geospatial/repositories/__init__.py
dbdaora/geospatial/repositories/datastore.py
dbdaora/geospatial/repositories/mongodb.py
dbdaora/geospatial/service/__init__.py
dbdaora/geospatial/service/datastore.py
dbdaora/geospatial/service/mongodb.py
dbdaora/hash/__init__.py
dbdaora/hash/conftest.py
dbdaora/hash/factory.py
dbdaora/hash/query.py
dbdaora/hash/repositories/__init__.py
dbdaora/hash/repositories/datastore.py
dbdaora/hash/repositories/mongodb.py
dbdaora/hash/service/__init__.py
dbdaora/hash/service/datastore.py
dbdaora/hash/service/mongodb.py
dbdaora/repository/__init__.py
dbdaora/repository/datastore.py
dbdaora/service/__init__.py
dbdaora/service/builder.py
dbdaora/sorted_set/__init__.py
dbdaora/sorted_set/conftest.py
dbdaora/sorted_set/entity.py
dbdaora/sorted_set/factory.py
dbdaora/sorted_set/query.py
dbdaora/sorted_set/repositories/__init__.py
dbdaora/sorted_set/repositories/datastore.py
dbdaora/sorted_set/repositories/mongodb.py
dbdaora/sorted_set/service/__init__.py
dbdaora/sorted_set/service/datastore.py
dbdaora/sorted_set/service/mongodb.py
dbdaora-0.27.0.dist-info/LICENSE
dbdaora-0.27.0.dist-info/WHEEL
dbdaora-0.27.0.dist-info/METADATA
dbdaora-0.27.0.dist-info/RECORD
