Metadata-Version: 2.1
Name: dbdaora
Version: 0.27.0
Summary: Communicates with databases using repository pattern and service patterns
Home-page: https://github.com/dutradda/dbdaora
License: UNKNOWN
Author: Diogo Dutra
Author-email: diogodutradamata@gmail.com
Requires-Python: >=3.8
Classifier: License :: OSI Approved :: MIT License
Classifier: Intended Audience :: Developers
Classifier: Programming Language :: Python :: 3.8
Classifier: Programming Language :: Python :: 3 :: Only
Classifier: Topic :: Database
Requires-Dist: circuitbreaker
Requires-Dist: cachetools
Requires-Dist: jsondaora
Requires-Dist: aioredis ; extra == "aioredis"
Requires-Dist: google-cloud-datastore ; extra == "datastore"
Requires-Dist: mkdocs ; extra == "doc"
Requires-Dist: mkdocs-material ; extra == "doc"
Requires-Dist: markdown-include ; extra == "doc"
Requires-Dist: motor ; extra == "mongodb"
Requires-Dist: newrelic ; extra == "newrelic"
Requires-Dist: black ; extra == "test"
Requires-Dist: isort ; extra == "test"
Requires-Dist: ipython ; extra == "test"
Requires-Dist: mypy ; extra == "test"
Requires-Dist: pytest-asyncio ; extra == "test"
Requires-Dist: pytest-cov ; extra == "test"
Requires-Dist: pytest-mock ; extra == "test"
Requires-Dist: pytest ; extra == "test"
Project-URL: Documentation, https://dutradda.github.io/dbdaora/
Provides-Extra: aioredis
Provides-Extra: datastore
Provides-Extra: doc
Provides-Extra: mongodb
Provides-Extra: newrelic
Provides-Extra: test
